discord_components_paginator/__init__.py
discord_components_paginator/paginator.py
discord_components_paginator-1.0.1.dist-info/LICENSE
discord_components_paginator-1.0.1.dist-info/METADATA
discord_components_paginator-1.0.1.dist-info/WHEEL
discord_components_paginator-1.0.1.dist-info/top_level.txt
discord_components_paginator-1.0.1.dist-info/RECORD
